masto_cli/__init__.py
masto_cli/config.py
masto_cli/favourite.py
masto_cli/profile.py
masto_cli/timeline.py
masto_cli/auth_user/__init__.py
masto_cli/auth_user/auth.py
masto_cli/publish/__init__.py
masto_cli/publish/publish.py
masto_cli/sign_in/html_parser.py
masto_cli/sign_in/http_client.py
masto_cli/sign_in/sign_in.py
test/test.py
masto_cli-0.2.0.dist-info/METADATA
masto_cli-0.2.0.dist-info/WHEEL
masto_cli-0.2.0.dist-info/top_level.txt
masto_cli-0.2.0.dist-info/RECORD
