Metadata-Version: 2.4
Name: masto_cli
Version: 0.2.0
Summary: Mastodon wrapper
Author: Rafi khalbi
License: MIT
Requires-Python: >=3.8
Requires-Dist: beautifulsoup4==4.13.4
Requires-Dist: bs4==0.0.2
Requires-Dist: certifi==2025.4.26
Requires-Dist: charset-normalizer==3.4.2
Requires-Dist: idna==3.10
Requires-Dist: requests==2.32.4
Requires-Dist: soupsieve==2.7
Requires-Dist: typing_extensions==4.14.0
Requires-Dist: urllib3==2.4.0
